persty/__init__.py
persty/delaunay.py
persty/minibox.py
persty/util.py
persty/cpp/__init__.py
persty/cpp/binding.cp38-win_amd64.pyd
persty-2.0.1.dist-info/LICENSE
persty-2.0.1.dist-info/METADATA
persty-2.0.1.dist-info/WHEEL
persty-2.0.1.dist-info/top_level.txt
persty-2.0.1.dist-info/RECORD
