Metadata-Version: 2.1
Name: persty
Version: 2.0.1
Summary: Implementation of Minibox and Delauany edges algorithms.
Home-page: https://github.com/gbeltramo/persty
Author: Gabriele Beltramo
License: GPLv3
Keywords: topology data analysis,minibox graph,delaunay graph
Platform: UNKNOWN
Requires-Dist: numpy
Requires-Dist: scipy
